hk_cdp/__init__.py
hk_cdp/handler/__init__.py
hk_cdp/handler/cdp_base.py
hk_cdp/libs/__init__.py
hk_cdp/libs/customize/__init__.py
hk_cdp/libs/customize/asset_base_model.py
hk_cdp/libs/customize/cdp_helper.py
hk_cdp/libs/customize/jd_spi_helper.py
hk_cdp/libs/customize/rainbow_helper.py
hk_cdp/libs/customize/tiktok_spi_helper.py
hk_cdp/libs/customize/work_base_model.py
hk_cdp/models/__init__.py
hk_cdp/models/cdp_model.py
hk_cdp/models/enum.py
hk_cdp/models/db_models/__init__.py
hk_cdp/models/db_models/analysis/__init__.py
hk_cdp/models/db_models/analysis/analysis_goods_related_model.py
hk_cdp/models/db_models/analysis/analysis_goods_repurchase_model.py
hk_cdp/models/db_models/analysis/analysis_report_model.py
hk_cdp/models/db_models/cap/__init__.py
hk_cdp/models/db_models/cap/cap_business_info_model.py
hk_cdp/models/db_models/cap/cap_store_info_model.py
hk_cdp/models/db_models/cdp/__init__.py
hk_cdp/models/db_models/cdp/cdp_store_info_model.py
hk_cdp/models/db_models/cdp/cdp_work_info_model.py
hk_cdp/models/db_models/jd/__init__.py
hk_cdp/models/db_models/jd/jd_integral_sync_model.py
hk_cdp/models/db_models/jd/jd_member_sync_model.py
hk_cdp/models/db_models/jd/jd_user_data_model.py
hk_cdp/models/db_models/member/__init__.py
hk_cdp/models/db_models/member/member_asset_log_model.py
hk_cdp/models/db_models/member/member_asset_model.py
hk_cdp/models/db_models/member/member_asset_only_model.py
hk_cdp/models/db_models/member/member_asset_valid_model.py
hk_cdp/models/db_models/member/member_event_model.py
hk_cdp/models/db_models/member/member_info_model.py
hk_cdp/models/db_models/member/member_level_log_model.py
hk_cdp/models/db_models/open/__init__.py
hk_cdp/models/db_models/open/open_item_model.py
hk_cdp/models/db_models/open/open_refund_model.py
hk_cdp/models/db_models/open/open_trade_model.py
hk_cdp/models/db_models/prefix/__init__.py
hk_cdp/models/db_models/prefix/prefix_info_model.py
hk_cdp/models/db_models/queue/__init__.py
hk_cdp-1.0.148.dist-info/LICENSE
hk_cdp-1.0.148.dist-info/METADATA
hk_cdp-1.0.148.dist-info/WHEEL
hk_cdp-1.0.148.dist-info/top_level.txt
hk_cdp-1.0.148.dist-info/RECORD
